cli/__init__.py
cli/main.py
sodaflow-2.0.4.dist-info/DESCRIPTION.rst
sodaflow-2.0.4.dist-info/METADATA
sodaflow-2.0.4.dist-info/RECORD
sodaflow-2.0.4.dist-info/WHEEL
sodaflow-2.0.4.dist-info/entry_points.txt
sodaflow-2.0.4.dist-info/metadata.json
sodaflow-2.0.4.dist-info/top_level.txt
