Metadata-Version: 2.0
Name: sodaflow
Version: 2.0.4
Summary: Greet someone
Home-page: UNKNOWN
Author: agilesoda
Author-email: agilesoda@gmail.com
License: UNKNOWN
Platform: UNKNOWN
Requires-Dist: click
Requires-Dist: requests
